setup.py
ratelimit_manager.egg-info/PKG-INFO
ratelimit_manager.egg-info/SOURCES.txt
ratelimit_manager.egg-info/dependency_links.txt
ratelimit_manager.egg-info/requires.txt
ratelimit_manager.egg-info/top_level.txt
rlmanager/__init__.py