Metadata-Version: 1.0
Name: ratelimit-manager
Version: 0.0.1
Summary: ratelimit manager
Home-page: https://github.com/tomotaka/ratelimit-manager
Author: Tomotaka Ito
Author-email: tomotaka.ito@gmail.com
License: MIT License
Platform: UNKNOWN
